bd_kernel_vulns/BOMClass.py
bd_kernel_vulns/ComponentClass.py
bd_kernel_vulns/ComponentListClass.py
bd_kernel_vulns/ConfigClass.py
bd_kernel_vulns/KernelSourceClass.py
bd_kernel_vulns/VulnClass.py
bd_kernel_vulns/VulnListClass.py
bd_kernel_vulns/__init__.py
bd_kernel_vulns/main.py
bd_kernel_vulns-1.0.6.dist-info/licenses/LICENSE
bd_kernel_vulns-1.0.6.dist-info/METADATA
bd_kernel_vulns-1.0.6.dist-info/WHEEL
bd_kernel_vulns-1.0.6.dist-info/entry_points.txt
bd_kernel_vulns-1.0.6.dist-info/top_level.txt
bd_kernel_vulns-1.0.6.dist-info/RECORD
