Metadata-Version: 2.4
Name: bd_kernel_vulns
Version: 1.0.6
Summary: bd_kernel_vulns - Script to process the Linux Kernel in a BD project to assess vulns applicability based on supplied list of kernel source files (or folders)
Author-email: Matthew Brady <mbrad@blackduck.com>
Project-URL: Homepage, https://github.com/blackducksoftware/bd_kernel_vulns
Project-URL: Issues, https://github.com/blackducksoftware/bd_kernel_vulns/issues
Classifier: Programming Language :: Python :: 3
Classifier: License :: OSI Approved :: MIT License
Classifier: Operating System :: OS Independent
Requires-Python: >=3.8
License-File: LICENSE
Requires-Dist: blackduck>=1.1.3
Requires-Dist: requests
Requires-Dist: aiohttp
Requires-Dist: asyncio
Dynamic: license-file
